fir_filter.v
module fir_filter(
    input clk,
    input reset,
    input signed [7:0] x,
    output reg signed [15:0] y
);

reg signed [7:0] h[0:2]; // coefficients
reg signed [7:0] x_reg[0:2];

integer i;

initial begin
    h[0] = 1;
    h[1] = 2;
    h[2] = 1;
end

always @(posedge clk) begin
    if (reset) begin
        for(i=0;i<3;i=i+1)
            x_reg[i] <= 0;
        y <= 0;
    end else begin
        // shift register
        x_reg[2] <= x_reg[1];
        x_reg[1] <= x_reg[0];
        x_reg[0] <= x;

        // FIR equation
        y <= h[0]*x_reg[0] + h[1]*x_reg[1] + h[2]*x_reg[2];
    end
end

endmodule

fir_filter_tb.v
module fir_filter_tb;

reg clk, reset;
reg signed [7:0] x;
wire signed [15:0] y;

fir_filter uut(
    .clk(clk),
    .reset(reset),
    .x(x),
    .y(y)
);

// clock generation
always #5 clk = ~clk;

initial begin
    clk = 0;
    reset = 1;
    x = 0;

    #10 reset = 0;

    // input samples
    #10 x = 1;
    #10 x = 2;
    #10 x = 3;
    #10 x = 4;
    #10 x = 5;

    #50 $finish;
end

initial begin
    $dumpfile("fir.vcd");
    $dumpvars(0, fir_filter_tb);
end

endmodule

fir.vcd
$date
	Thu Apr 02 17:55:43 2026
$end
$version
	Icarus Verilog
$end
$timescale
	1s
$end
$scope module fir_filter_tb $end
$var wire 16 ! y [15:0] $end
$var reg 1 " clk $end
$var reg 1 # reset $end
$var reg 8 $ x [7:0] $end
$scope module uut $end
$var wire 1 " clk $end
$var wire 1 # reset $end
$var wire 8 % x [7:0] $end
$var reg 16 & y [15:0] $end
$var integer 32 ' i [31:0] $end
$upscope $end
$upscope $end
$enddefinitions $end
$comment Show the parameter values. $end
$dumpall
$end
#0
$dumpvars
bx '
bx &
b0 %
b0 $
1#
0"
bx !
$end
#5
b0 !
b0 &
b11 '
1"
#10
0"
0#
#15
1"
#20
0"
b1 $
b1 %
#25
1"
#30
0"
b10 $
b10 %
#35
b1 !
b1 &
1"
#40
0"
b11 $
b11 %
#45
b100 !
b100 &
1"
#50
0"
b100 $
b100 %
#55
b1000 !
b1000 &
1"
#60
0"
b101 $
b101 %
#65
b1100 !
b1100 &
1"
#70
0"
#75
b10000 !
b10000 &
1"
#80
0"
#85
b10011 !
b10011 &
1"
#90
0"
#95
b10100 !
b10100 &
1"
